{
  "format_version": "1.14.0",
  "sound_definitions": {
    "orchiella:sraw_explode": {
      "category": "player",
      "sounds": [
        {
          "name": "sounds/sraw/explode",
          "stream": false
        }
      ]
    },
    "orchiella:sraw_aim": {
      "category": "player",
      "sounds": [
        {
          "name": "sounds/sraw/aim",
          "stream": false
        }
      ]
    },
    "orchiella:sraw_fire": {
      "category": "player",
      "sounds": [
        {
          "name": "sounds/sraw/fire",
          "stream": false
        }
      ]
    }
  }
}